[{"Letter":"T1","DepartureTime":"2022-01-04T17:50:00+00:00","PlannedDepartureTime":"2022-01-04T17:50:00+00:00","LinesEn":["Boarding closed",""],"LinesFr":["Embarquement terminé",""],"FormattedDepartureTimes":{"OriginalDepatureTime":"2022-01-04T17:50:00+00:00","DeparturesDateOffset":60,"FormattedFolkestoneTerminalTime":"18:50","FormattedCalaisTerminalTime":"18:50"}},{"Letter":"T3","DepartureTime":"2022-01-04T17:50:00+00:00","PlannedDepartureTime":"2022-01-04T17:50:00+00:00","LinesEn":["Boarding closed",""],"LinesFr":["Embarquement terminé",""],"FormattedDepartureTimes":{"OriginalDepatureTime":"2022-01-04T17:50:00+00:00","DeparturesDateOffset":60,"FormattedFolkestoneTerminalTime":"18:50","FormattedCalaisTerminalTime":"18:50"}},{"Letter":"T5","DepartureTime":"2022-01-04T17:50:00+00:00","PlannedDepartureTime":"2022-01-04T17:50:00+00:00","LinesEn":["Boarding closed",""],"LinesFr":["Embarquement terminé",""],"FormattedDepartureTimes":{"OriginalDepatureTime":"2022-01-04T17:50:00+00:00","DeparturesDateOffset":60,"FormattedFolkestoneTerminalTime":"18:50","FormattedCalaisTerminalTime":"18:50"}},{"Letter":"U1","DepartureTime":"2022-01-04T18:19:00+00:00","PlannedDepartureTime":"2022-01-04T18:19:00+00:00","LinesEn":["Last call","Boarding imminent"],"LinesFr":["Dernier appel","Embarquement imminent"],"FormattedDepartureTimes":{"OriginalDepatureTime":"2022-01-04T18:19:00+00:00","DeparturesDateOffset":60,"FormattedFolkestoneTerminalTime":"19:19","FormattedCalaisTerminalTime":"19:19"}},{"Letter":"U3","DepartureTime":"2022-01-04T18:19:00+00:00","PlannedDepartureTime":"2022-01-04T18:19:00+00:00","LinesEn":["Please proceed","Boarding imminent"],"LinesFr":["Appel en cours","Embarquement imminent"],"FormattedDepartureTimes":{"OriginalDepatureTime":"2022-01-04T18:19:00+00:00","DeparturesDateOffset":60,"FormattedFolkestoneTerminalTime":"19:19","FormattedCalaisTerminalTime":"19:19"}},{"Letter":"U5","DepartureTime":"2022-01-04T18:19:00+00:00","PlannedDepartureTime":"2022-01-04T18:19:00+00:00","LinesEn":["Please proceed","Boarding imminent"],"LinesFr":["Appel en cours","Embarquement imminent"],"FormattedDepartureTimes":{"OriginalDepatureTime":"2022-01-04T18:19:00+00:00","DeparturesDateOffset":60,"FormattedFolkestoneTerminalTime":"19:19","FormattedCalaisTerminalTime":"19:19"}},{"Letter":"V1","DepartureTime":"2022-01-04T18:50:00+00:00","PlannedDepartureTime":"2022-01-04T18:50:00+00:00","LinesEn":["Please proceed"],"LinesFr":["Appel en cours"],"FormattedDepartureTimes":{"OriginalDepatureTime":"2022-01-04T18:50:00+00:00","DeparturesDateOffset":60,"FormattedFolkestoneTerminalTime":"19:50","FormattedCalaisTerminalTime":"19:50"}},{"Letter":"V3","DepartureTime":"2022-01-04T18:50:00+00:00","PlannedDepartureTime":"2022-01-04T18:50:00+00:00","LinesEn":["Please proceed"],"LinesFr":["Appel en cours"],"FormattedDepartureTimes":{"OriginalDepatureTime":"2022-01-04T18:50:00+00:00","DeparturesDateOffset":60,"FormattedFolkestoneTerminalTime":"19:50","FormattedCalaisTerminalTime":"19:50"}},{"Letter":"V5","DepartureTime":"2022-01-04T18:50:00+00:00","PlannedDepartureTime":"2022-01-04T18:50:00+00:00","LinesEn":["First call in 5m",""],"LinesFr":["Premier appel 5m",""],"FormattedDepartureTimes":{"OriginalDepatureTime":"2022-01-04T18:50:00+00:00","DeparturesDateOffset":60,"FormattedFolkestoneTerminalTime":"19:50","FormattedCalaisTerminalTime":"19:50"}},{"Letter":"W1","DepartureTime":"2022-01-04T19:20:00+00:00","PlannedDepartureTime":"2022-01-04T19:20:00+00:00","LinesEn":["First call in 15m",""],"LinesFr":["Premier appel 15m",""],"FormattedDepartureTimes":{"OriginalDepatureTime":"2022-01-04T19:20:00+00:00","DeparturesDateOffset":60,"FormattedFolkestoneTerminalTime":"20:20","FormattedCalaisTerminalTime":"20:20"}},{"Letter":"W3","DepartureTime":"2022-01-04T19:20:00+00:00","PlannedDepartureTime":"2022-01-04T19:20:00+00:00","LinesEn":["First call in 20m",""],"LinesFr":["Premier appel 20m",""],"FormattedDepartureTimes":{"OriginalDepatureTime":"2022-01-04T19:20:00+00:00","DeparturesDateOffset":60,"FormattedFolkestoneTerminalTime":"20:20","FormattedCalaisTerminalTime":"20:20"}},{"Letter":"W5","DepartureTime":"2022-01-04T19:20:00+00:00","PlannedDepartureTime":"2022-01-04T19:20:00+00:00","LinesEn":["First call in 35m",""],"LinesFr":["Premier appel 35m",""],"FormattedDepartureTimes":{"OriginalDepatureTime":"2022-01-04T19:20:00+00:00","DeparturesDateOffset":60,"FormattedFolkestoneTerminalTime":"20:20","FormattedCalaisTerminalTime":"20:20"}},{"Letter":"X1","DepartureTime":"2022-01-04T19:50:00+00:00","PlannedDepartureTime":"2022-01-04T19:50:00+00:00","LinesEn":["First call in 45m",""],"LinesFr":["Premier appel 45m",""],"FormattedDepartureTimes":{"OriginalDepatureTime":"2022-01-04T19:50:00+00:00","DeparturesDateOffset":60,"FormattedFolkestoneTerminalTime":"20:50","FormattedCalaisTerminalTime":"20:50"}},{"Letter":"X3","DepartureTime":"2022-01-04T19:50:00+00:00","PlannedDepartureTime":"2022-01-04T19:50:00+00:00","LinesEn":["First call in 50m",""],"LinesFr":["Premier appel 50m",""],"FormattedDepartureTimes":{"OriginalDepatureTime":"2022-01-04T19:50:00+00:00","DeparturesDateOffset":60,"FormattedFolkestoneTerminalTime":"20:50","FormattedCalaisTerminalTime":"20:50"}},{"Letter":"X5","DepartureTime":"2022-01-04T19:50:00+00:00","PlannedDepartureTime":"2022-01-04T19:50:00+00:00","LinesEn":["Wait for call","First call in 1h 5m"],"LinesFr":["Attendez l'appel","Premier appel 1h 5m"],"FormattedDepartureTimes":{"OriginalDepatureTime":"2022-01-04T19:50:00+00:00","DeparturesDateOffset":60,"FormattedFolkestoneTerminalTime":"20:50","FormattedCalaisTerminalTime":"20:50"}},{"Letter":"Y1","DepartureTime":"2022-01-04T20:17:00+00:00","PlannedDepartureTime":"2022-01-04T20:17:00+00:00","LinesEn":["Wait for call","First call in 1h 12m"],"LinesFr":["Attendez l'appel","Premier appel 1h 12m"],"FormattedDepartureTimes":{"OriginalDepatureTime":"2022-01-04T20:17:00+00:00","DeparturesDateOffset":60,"FormattedFolkestoneTerminalTime":"21:17","FormattedCalaisTerminalTime":"21:17"}},{"Letter":"Y3","DepartureTime":"2022-01-04T20:17:00+00:00","PlannedDepartureTime":"2022-01-04T20:17:00+00:00","LinesEn":["Wait for call","First call in 1h 17m"],"LinesFr":["Attendez l'appel","Premier appel 1h 17m"],"FormattedDepartureTimes":{"OriginalDepatureTime":"2022-01-04T20:17:00+00:00","DeparturesDateOffset":60,"FormattedFolkestoneTerminalTime":"21:17","FormattedCalaisTerminalTime":"21:17"}},{"Letter":"Y5","DepartureTime":"2022-01-04T20:17:00+00:00","PlannedDepartureTime":"2022-01-04T20:17:00+00:00","LinesEn":["Wait for call","First call in 1h 32m"],"LinesFr":["Attendez l'appel","Premier appel 1h 32m"],"FormattedDepartureTimes":{"OriginalDepatureTime":"2022-01-04T20:17:00+00:00","DeparturesDateOffset":60,"FormattedFolkestoneTerminalTime":"21:17","FormattedCalaisTerminalTime":"21:17"}},{"Letter":"Z1","DepartureTime":"2022-01-04T20:50:00+00:00","PlannedDepartureTime":"2022-01-04T20:50:00+00:00","LinesEn":["Wait for call","First call in 1h 45m"],"LinesFr":["Attendez l'appel","Premier appel 1h 45m"],"FormattedDepartureTimes":{"OriginalDepatureTime":"2022-01-04T20:50:00+00:00","DeparturesDateOffset":60,"FormattedFolkestoneTerminalTime":"21:50","FormattedCalaisTerminalTime":"21:50"}},{"Letter":"Z5","DepartureTime":"2022-01-04T20:50:00+00:00","PlannedDepartureTime":"2022-01-04T20:50:00+00:00","LinesEn":["Wait for call","First call in 2h 5m"],"LinesFr":["Attendez l'appel","Premier appel 2h 5m"],"FormattedDepartureTimes":{"OriginalDepatureTime":"2022-01-04T20:50:00+00:00","DeparturesDateOffset":60,"FormattedFolkestoneTerminalTime":"21:50","FormattedCalaisTerminalTime":"21:50"}}]